<?xml version="1.0" encoding="UTF-8"?>
<Tokens version="1.0">
	<File path="Classes/AWSAutoScalingLoadBalancerTargetGroupState.html">
		
		<Token>
			<TokenIdentifier>//apple_ref/occ/cl/AWSAutoScalingLoadBalancerTargetGroupState</TokenIdentifier>
			<Abstract type="html"></Abstract>
			<DeclaredIn>AWSAutoScalingModel.h</DeclaredIn>
            
			
			<NodeRef refid="76"/>
		</Token>
		
		
		<Token>
			<TokenIdentifier>//apple_ref/occ/instm/AWSAutoScalingLoadBalancerTargetGroupState/setLoadBalancerTargetGroupARN:</TokenIdentifier>
			<Abstract type="html"></Abstract>
			<DeclaredIn>AWSAutoScalingModel.h</DeclaredIn>
			
			<Declaration>@property (nonatomic, strong) NSString *loadBalancerTargetGroupARN</Declaration>
			
			
			<Anchor>//api/name/loadBalancerTargetGroupARN</Anchor>
            <NodeRef refid="76"/>
		</Token>
		
		<Token>
			<TokenIdentifier>//apple_ref/occ/instm/AWSAutoScalingLoadBalancerTargetGroupState/loadBalancerTargetGroupARN</TokenIdentifier>
			<Abstract type="html"></Abstract>
			<DeclaredIn>AWSAutoScalingModel.h</DeclaredIn>
			
			<Declaration>@property (nonatomic, strong) NSString *loadBalancerTargetGroupARN</Declaration>
			
			
			<Anchor>//api/name/loadBalancerTargetGroupARN</Anchor>
            <NodeRef refid="76"/>
		</Token>
		
		<Token>
			<TokenIdentifier>//apple_ref/occ/instp/AWSAutoScalingLoadBalancerTargetGroupState/loadBalancerTargetGroupARN</TokenIdentifier>
			<Abstract type="html"></Abstract>
			<DeclaredIn>AWSAutoScalingModel.h</DeclaredIn>
			
			<Declaration>@property (nonatomic, strong) NSString *loadBalancerTargetGroupARN</Declaration>
			
			
			<Anchor>//api/name/loadBalancerTargetGroupARN</Anchor>
            <NodeRef refid="76"/>
		</Token>
		
		<Token>
			<TokenIdentifier>//apple_ref/occ/instm/AWSAutoScalingLoadBalancerTargetGroupState/setState:</TokenIdentifier>
			<Abstract type="html"></Abstract>
			<DeclaredIn>AWSAutoScalingModel.h</DeclaredIn>
			
			<Declaration>@property (nonatomic, strong) NSString *state</Declaration>
			
			
			<Anchor>//api/name/state</Anchor>
            <NodeRef refid="76"/>
		</Token>
		
		<Token>
			<TokenIdentifier>//apple_ref/occ/instm/AWSAutoScalingLoadBalancerTargetGroupState/state</TokenIdentifier>
			<Abstract type="html"></Abstract>
			<DeclaredIn>AWSAutoScalingModel.h</DeclaredIn>
			
			<Declaration>@property (nonatomic, strong) NSString *state</Declaration>
			
			
			<Anchor>//api/name/state</Anchor>
            <NodeRef refid="76"/>
		</Token>
		
		<Token>
			<TokenIdentifier>//apple_ref/occ/instp/AWSAutoScalingLoadBalancerTargetGroupState/state</TokenIdentifier>
			<Abstract type="html"></Abstract>
			<DeclaredIn>AWSAutoScalingModel.h</DeclaredIn>
			
			<Declaration>@property (nonatomic, strong) NSString *state</Declaration>
			
			
			<Anchor>//api/name/state</Anchor>
            <NodeRef refid="76"/>
		</Token>
		
        
        
	</File>
</Tokens>